_libpasta.so
libpasta.py
libpasta-0.0.6.dist-info/DESCRIPTION.rst
libpasta-0.0.6.dist-info/metadata.json
libpasta-0.0.6.dist-info/top_level.txt
libpasta-0.0.6.dist-info/WHEEL
libpasta-0.0.6.dist-info/METADATA
libpasta-0.0.6.dist-info/RECORD
.libs_libpasta/libcrypto-de69073a.so.0.9.8e
.libs_libpasta/libk5crypto-622ef25b.so.3.1
.libs_libpasta/libssl-a65b360f.so.0.9.8e
.libs_libpasta/libcom_err-beb60336.so.2.1
.libs_libpasta/libkrb5support-d7ce89d4.so.0.1
.libs_libpasta/libz-a147dcb0.so.1.2.3
.libs_libpasta/libgssapi_krb5-174f8956.so.2.2
.libs_libpasta/libkrb5-fb0d2caa.so.3.3
.libs_libpasta/libsepol-b4f5b513.so.1
.libs_libpasta/libselinux-cf8f9094.so.1
.libs_libpasta/libkeyutils-1-ff31573b.2.so
