Metadata-Version: 2.0
Name: libpasta
Version: 0.0.6
Summary: Password hashing library
Home-page: https://libpasta.github.io/
Author: Sam Scott
Author-email: me@samjs.co.uk
License: MIT
Platform: any
Classifier: Development Status :: 1 - Planning
Classifier: Intended Audience :: Developers
Classifier: License :: OSI Approved :: MIT License
Classifier: Operating System :: OS Independent
Classifier: Programming Language :: Python
Classifier: Topic :: Security :: Cryptography
Classifier: Topic :: Software Development :: Libraries :: Python Modules
